gamma_micro_cross/__init__.py
gamma_micro_cross/gamma_micro_cross.py
gamma_micro_cross-0.0.5.dist-info/LICENSE
gamma_micro_cross-0.0.5.dist-info/METADATA
gamma_micro_cross-0.0.5.dist-info/WHEEL
gamma_micro_cross-0.0.5.dist-info/top_level.txt
gamma_micro_cross-0.0.5.dist-info/RECORD
